gprof2dot.py
gprof2dot-2024.6.5.dist-info/LICENSE.txt
gprof2dot-2024.6.5.dist-info/METADATA
gprof2dot-2024.6.5.dist-info/WHEEL
gprof2dot-2024.6.5.dist-info/entry_points.txt
gprof2dot-2024.6.5.dist-info/top_level.txt
gprof2dot-2024.6.5.dist-info/RECORD
