Metadata-Version: 2.1
Name: gprof2dot
Version: 2024.6.5
Summary: Generate a dot graph from the output of several profilers.
Home-page: https://github.com/jrfonseca/gprof2dot
Author: Jose Fonseca
Author-email: jose.r.fonseca@gmail.com
License: LGPL
Classifier: Development Status :: 6 - Mature
Classifier: Environment :: Console
Classifier: Intended Audience :: Developers
Classifier: Operating System :: OS Independent
Classifier: License :: OSI Approved :: GNU Lesser General Public License v3 or later (LGPLv3+)
Classifier: Programming Language :: Python :: 3
Classifier: Topic :: Software Development
Requires-Python: >=2.7
License-File: LICENSE.txt
